models/__init__.py
models/common.py
models/experimental.py
models/tf.py
models/yolo.py
utils/__init__.py
utils/activations.py
utils/augmentations.py
utils/autoanchor.py
utils/callbacks.py
utils/datasets.py
utils/downloads.py
utils/general.py
utils/loss.py
utils/metrics.py
utils/plots.py
utils/torch_utils.py
utils/aws/__init__.py
utils/aws/resume.py
utils/loggers/__init__.py
utils/loggers/wandb/__init__.py
utils/loggers/wandb/log_dataset.py
utils/loggers/wandb/sweep.py
utils/loggers/wandb/wandb_utils.py
dna_yolov5_torch-1.0.1.dist-info/METADATA
dna_yolov5_torch-1.0.1.dist-info/WHEEL
dna_yolov5_torch-1.0.1.dist-info/top_level.txt
dna_yolov5_torch-1.0.1.dist-info/RECORD
